three60cube/__init__.py
three60cube/three60cube.py
three60cube-0.0.9.dist-info/METADATA
three60cube-0.0.9.dist-info/WHEEL
three60cube-0.0.9.dist-info/top_level.txt
three60cube-0.0.9.dist-info/RECORD
