Metadata-Version: 2.1
Name: three60cube
Version: 0.0.9
Summary: A class to project 360x180 images onto a cube
Home-page: https://github.com/UtrechtUniversity/three60cube
Author: C.S. Kaandorp
Author-email: c.s.kaandorp@uu.nl
License: MIT
Platform: UNKNOWN
Requires-Python: >=3.6
Requires-Dist: pillow
Requires-Dist: numpy
Requires-Dist: scipy
Requires-Dist: sklearn
